{
  "subjects": {
    "math_6": {
      "name": "ุงูุฑูุงุถูุงุช - ุงูุณูุฉ ุงูุณุงุฏุณุฉ",
      "icon": "๐ข",
      "color": "#e53e3e",
      "lessons": [
        {
          "id": "math_6_lesson_1",
          "title": "ุงูุฃุนุฏุงุฏ ุงูุตุญูุญุฉ",
          "chapter": 1,
          "duration": "45 ุฏูููุฉ",
          "summary": "ูู ูุฐุง ุงูุฏุฑุณ ุณูุชุนุฑู ุนูู ุงูุฃุนุฏุงุฏ ุงูุตุญูุญุฉ ูุฎุตุงุฆุตูุง. ุงูุฃุนุฏุงุฏ ุงูุตุญูุญุฉ ุชุดูู ุงูุฃุนุฏุงุฏ ุงูููุฌุจุฉ ูุงูุฃุนุฏุงุฏ ุงูุณุงูุจุฉ ูุงูุตูุฑ. ุณูุชุนูู ููููุฉ ููุงุฑูุฉ ุงูุฃุนุฏุงุฏ ุงูุตุญูุญุฉ ูุชูุซูููุง ุนูู ุฎุท ุงูุฃุนุฏุงุฏ.",
          "video_url": "https://www.youtube.com/embed/dQw4w9WgXcQ",
          "learning_objectives": [
            "ุชุญุฏูุฏ ุงูุฃุนุฏุงุฏ ุงูุตุญูุญุฉ ูุชุตููููุง",
            "ููุงุฑูุฉ ุงูุฃุนุฏุงุฏ ุงูุตุญูุญุฉ",
            "ุชูุซูู ุงูุฃุนุฏุงุฏ ุนูู ุฎุท ุงูุฃุนุฏุงุฏ",
            "ุฅุฌุฑุงุก ุงูุนูููุงุช ุงูุญุณุงุจูุฉ ุนูู ุงูุฃุนุฏุงุฏ ุงูุตุญูุญุฉ"
          ],
          "exercises": [
            {
              "id": "ex_1",
              "type": "multiple_choice",
              "question": "ุฃู ูู ุงูุฃุนุฏุงุฏ ุงูุชุงููุฉ ุฃุตุบุฑ ูู -5ุ",
              "options": [
                "-3",
                "-7",
                "0",
                "5"
              ],
              "correct_answer": 1,
              "explanation": "ุงูุนุฏุฏ -7 ุฃุตุบุฑ ูู -5 ูุฃูู ุฃุจุนุฏ ุนูู ูุณุงุฑ ุฎุท ุงูุฃุนุฏุงุฏ"
            },
            {
              "id": "ex_2",
              "type": "fill_blank",
              "question": "ุงูุนุฏุฏ ุงูุตุญูุญ ุจูู -2 ู 2 ูู ___",
              "correct_answer": "0",
              "acceptable_answers": ["ุตูุฑ", "0", "ุงูุตูุฑ"],
              "explanation": "ุงูุตูุฑ ูู ุงูุนุฏุฏ ุงูููุฌูุฏ ุจูู -2 ู 2"
            },
            {
              "id": "ex_3",
              "type": "true_false",
              "question": "ุงูุนุฏุฏ -1 ุฃูุจุฑ ูู ุงูุนุฏุฏ -3",
              "correct_answer": true,
              "explanation": "ูุนูุ -1 ุฃูุจุฑ ูู -3 ูุฃูู ุฃูุฑุจ ุฅูู ุงูุตูุฑ"
            }
          ]
        },
        {
          "id": "math_6_lesson_2",
          "title": "ุงููุณูุฑ ุงูุนุดุฑูุฉ",
          "chapter": 2,
          "duration": "50 ุฏูููุฉ",
          "summary": "ุฏุฑุณ ุดุงูู ุนู ุงููุณูุฑ ุงูุนุดุฑูุฉ ูููููุฉ ุงูุชุนุงูู ูุนูุง. ุณูุชุนูู ูุฑุงุกุฉ ููุชุงุจุฉ ุงููุณูุฑ ุงูุนุดุฑูุฉ ูููุงุฑูุชูุง ูุฅุฌุฑุงุก ุงูุนูููุงุช ุงูุญุณุงุจูุฉ ุนูููุง.",
          "video_url": "https://www.youtube.com/embed/dQw4w9WgXcQ",
          "learning_objectives": [
            "ูุฑุงุกุฉ ููุชุงุจุฉ ุงููุณูุฑ ุงูุนุดุฑูุฉ",
            "ููุงุฑูุฉ ุงููุณูุฑ ุงูุนุดุฑูุฉ",
            "ุชุญููู ุงููุณูุฑ ุงูุงุนุชูุงุฏูุฉ ุฅูู ุนุดุฑูุฉ",
            "ุฌูุน ูุทุฑุญ ุงููุณูุฑ ุงูุนุดุฑูุฉ"
          ],
          "exercises": [
            {
              "id": "ex_1",
              "type": "multiple_choice",
              "question": "ูู ูุณุงูู 0.5 + 0.3ุ",
              "options": [
                "0.2",
                "0.8",
                "0.08",
                "8.0"
              ],
              "correct_answer": 1,
              "explanation": "0.5 + 0.3 = 0.8"
            }
          ]
        }
      ]
    },
    "arabic_6": {
      "name": "ุงููุบุฉ ุงูุนุฑุจูุฉ - ุงูุณูุฉ ุงูุณุงุฏุณุฉ",
      "icon": "๐",
      "color": "#667eea",
      "lessons": [
        {
          "id": "arabic_6_lesson_1",
          "title": "ุฃููุงุน ุงูุฃุณูุงุก",
          "chapter": 1,
          "duration": "40 ุฏูููุฉ",
          "summary": "ุชุนุฑู ุนูู ุฃููุงุน ุงูุฃุณูุงุก ูู ุงููุบุฉ ุงูุนุฑุจูุฉ: ุงูููุฑุฏ ูุงููุซูู ูุงูุฌูุน. ูุฃูุณุงู ุงูุฃุณูุงุก ูู ุญูุซ ุงูุชุฐููุฑ ูุงูุชุฃููุซ.",
          "video_url": "https://www.youtube.com/embed/dQw4w9WgXcQ",
          "learning_objectives": [
            "ุชุญุฏูุฏ ุฃููุงุน ุงูุฃุณูุงุก",
            "ุงูุชูููุฒ ุจูู ุงูููุฑุฏ ูุงููุซูู ูุงูุฌูุน",
            "ุชุทุจูู ุงูุฃุญูุงู ุงููุญููุฉ"
          ],
          "exercises": [
            {
              "id": "ex_1",
              "type": "fill_blank",
              "question": "ูููุฉ 'ูุนููุงู' ุชุฏู ุนูู ___",
              "correct_answer": "ูุซูู",
              "acceptable_answers": ["ุงุซููู", "ุงููุซูู"],
              "explanation": "ูุนููุงู ุชุฏู ุนูู ูุนูููู ุงุซููู (ูุซูู)"
            }
          ]
        }
      ]
    }
  }
}
